[
	{
		"Title": "Nachrichten, Wetter, Verkehr",
		"Subtitle": "",
		"Summary": "",
		"Description": "",
		"ChannelName": "BAYERN plus",
		"Start": "2018-09-12T00:00:00+02:00",
		"Stop": "2018-09-12T00:05:00+02:00",
		"Info": {}
	},
	{
		"Title": "Die Schlagernacht von BR und MDR",
		"Subtitle": "",
		"Summary": "",
		"Description": "jeweils zur vollen StundeNachrichten, Wetter, Verkehr",
		"ChannelName": "BAYERN plus",
		"Start": "2018-09-12T00:05:00+02:00",
		"Stop": "2018-09-12T06:00:00+02:00",
		"Info": {}
	},
	{
		"Title": "Nachrichten, Wetter, Verkehr",
		"Subtitle": "",
		"Summary": "",
		"Description": "",
		"ChannelName": "BAYERN plus",
		"Start": "2018-09-12T06:00:00+02:00",
		"Stop": "2018-09-12T06:05:00+02:00",
		"Info": {}
	},
	{
		"Title": "Bayern plus - Meine Schlager hören",
		"Subtitle": "",
		"Summary": "",
		"Description": "Jeweils zur vollen StundeNachrichten, Wetter, Verkehr",
		"ChannelName": "BAYERN plus",
		"Start": "2018-09-12T06:05:00+02:00",
		"Stop": "2018-09-12T07:00:00+02:00",
		"Info": {}
	},
	{
		"Title": "Nachrichten, Wetter, Verkehr",
		"Subtitle": "",
		"Summary": "",
		"Description": "",
		"ChannelName": "BAYERN plus",
		"Start": "2018-09-12T07:00:00+02:00",
		"Stop": "2018-09-12T07:05:00+02:00",
		"Info": {}
	},
	{
		"Title": "Bayern plus - Der Vormittag",
		"Subtitle": "",
		"Summary": "",
		"Description": "Das Wichtigste aus Bayern und der Welt, Service und interessante Gäste7.30 / 8.30 / 9.30 / 10.30Bayernnachrichten, Wetter8.00 / 9.00 / 10.00Nachrichten, Wetter, Verkehr",
		"ChannelName": "BAYERN plus",
		"Start": "2018-09-12T07:05:00+02:00",
		"Stop": "2018-09-12T11:00:00+02:00",
		"Info": {}
	},
	{
		"Title": "Nachrichten, Wetter, Verkehr",
		"Subtitle": "",
		"Summary": "",
		"Description": "",
		"ChannelName": "BAYERN plus",
		"Start": "2018-09-12T11:00:00+02:00",
		"Stop": "2018-09-12T11:05:00+02:00",
		"Info": {}
	},
	{
		"Title": "Bayern plus - Elf bis drei",
		"Subtitle": "",
		"Summary": "",
		"Description": "Das Wichtigste aus Bayern und der Welt, Service und interessante Gäste11.30 / 12.30 / 13.30 / 14.30Bayernnachrichten, Wetter12.00 / 13.00 / 14.00Nachrichten, Wetter, Verkehr",
		"ChannelName": "BAYERN plus",
		"Start": "2018-09-12T11:05:00+02:00",
		"Stop": "2018-09-12T15:00:00+02:00",
		"Info": {}
	},
	{
		"Title": "Nachrichten, Wetter, Verkehr",
		"Subtitle": "",
		"Summary": "",
		"Description": "",
		"ChannelName": "BAYERN plus",
		"Start": "2018-09-12T15:00:00+02:00",
		"Stop": "2018-09-12T15:05:00+02:00",
		"Info": {}
	},
	{
		"Title": "Bayern plus - Der Nachmittag",
		"Subtitle": "",
		"Summary": "",
		"Description": "",
		"ChannelName": "BAYERN plus",
		"Start": "2018-09-12T15:05:00+02:00",
		"Stop": "2018-09-12T18:00:00+02:00",
		"Info": {}
	},
	{
		"Title": "Nachrichten, Wetter, Verkehr",
		"Subtitle": "",
		"Summary": "",
		"Description": "",
		"ChannelName": "BAYERN plus",
		"Start": "2018-09-12T18:00:00+02:00",
		"Stop": "2018-09-12T18:05:00+02:00",
		"Info": {}
	},
	{
		"Title": "Bayern plus - Meine Schlager hören",
		"Subtitle": "",
		"Summary": "",
		"Description": "",
		"ChannelName": "BAYERN plus",
		"Start": "2018-09-12T18:05:00+02:00",
		"Stop": "2018-09-12T22:00:00+02:00",
		"Info": {}
	},
	{
		"Title": "Nachrichten, Wetter, Verkehr",
		"Subtitle": "",
		"Summary": "",
		"Description": "",
		"ChannelName": "BAYERN plus",
		"Start": "2018-09-12T22:00:00+02:00",
		"Stop": "2018-09-12T22:05:00+02:00",
		"Info": {}
	},
	{
		"Title": "Die Schlagernacht von BR und MDR",
		"Subtitle": "",
		"Summary": "",
		"Description": "",
		"ChannelName": "BAYERN plus",
		"Start": "2018-09-12T22:05:00+02:00",
		"Stop": "2018-09-13T00:00:00+02:00",
		"Info": {}
	}
]