[
	{
		"Title": "Bob Ross - The Joy of Painting",
		"Subtitle": "",
		"Summary": "",
		"Description": "",
		"ChannelName": "ARD-alpha",
		"Start": "2018-09-13T00:05:00+02:00",
		"Stop": "2018-09-13T00:35:00+02:00",
		"Info": {}
	},
	{
		"Title": "Space Night",
		"Subtitle": "",
		"Summary": "",
		"Description": "",
		"ChannelName": "ARD-alpha",
		"Start": "2018-09-13T00:35:00+02:00",
		"Stop": "2018-09-13T01:35:00+02:00",
		"Info": {}
	},
	{
		"Title": "alpha-centauri",
		"Subtitle": "",
		"Summary": "",
		"Description": "",
		"ChannelName": "ARD-alpha",
		"Start": "2018-09-13T01:35:00+02:00",
		"Stop": "2018-09-13T01:50:00+02:00",
		"Info": {}
	},
	{
		"Title": "Space Night CLASSICS",
		"Subtitle": "",
		"Summary": "",
		"Description": "",
		"ChannelName": "ARD-alpha",
		"Start": "2018-09-13T01:50:00+02:00",
		"Stop": "2018-09-13T02:30:00+02:00",
		"Info": {}
	},
	{
		"Title": "alpha-centauri",
		"Subtitle": "",
		"Summary": "",
		"Description": "",
		"ChannelName": "ARD-alpha",
		"Start": "2018-09-13T02:30:00+02:00",
		"Stop": "2018-09-13T02:45:00+02:00",
		"Info": {}
	},
	{
		"Title": "W wie Wissen",
		"Subtitle": "",
		"Summary": "",
		"Description": "",
		"ChannelName": "ARD-alpha",
		"Start": "2018-09-13T02:45:00+02:00",
		"Stop": "2018-09-13T03:15:00+02:00",
		"Info": {}
	},
	{
		"Title": "nano",
		"Subtitle": "",
		"Summary": "",
		"Description": "",
		"ChannelName": "ARD-alpha",
		"Start": "2018-09-13T03:15:00+02:00",
		"Stop": "2018-09-13T03:45:00+02:00",
		"Info": {}
	},
	{
		"Title": "Tele-Akademie",
		"Subtitle": "",
		"Summary": "",
		"Description": "",
		"ChannelName": "ARD-alpha",
		"Start": "2018-09-13T03:45:00+02:00",
		"Stop": "2018-09-13T04:30:00+02:00",
		"Info": {}
	},
	{
		"Title": "Planet Wissen: Welche Krankheiten kann die Genschere CRISPR heilen?",
		"Subtitle": "",
		"Summary": "",
		"Description": "",
		"ChannelName": "ARD-alpha",
		"Start": "2018-09-13T04:30:00+02:00",
		"Stop": "2018-09-13T05:30:00+02:00",
		"Info": {}
	},
	{
		"Title": "alpha-demokratie",
		"Subtitle": "",
		"Summary": "",
		"Description": "",
		"ChannelName": "ARD-alpha",
		"Start": "2018-09-13T05:30:00+02:00",
		"Stop": "2018-09-13T06:00:00+02:00",
		"Info": {}
	},
	{
		"Title": "Bob Ross - The Joy of Painting",
		"Subtitle": "",
		"Summary": "",
		"Description": "",
		"ChannelName": "ARD-alpha",
		"Start": "2018-09-13T06:00:00+02:00",
		"Stop": "2018-09-13T06:30:00+02:00",
		"Info": {}
	},
	{
		"Title": "Englisch für Anfänger - Übung (2/12)",
		"Subtitle": "",
		"Summary": "",
		"Description": "",
		"ChannelName": "ARD-alpha",
		"Start": "2018-09-13T06:30:00+02:00",
		"Stop": "2018-09-13T07:00:00+02:00",
		"Info": {}
	},
	{
		"Title": "Avanti! Avanti! (20/26)",
		"Subtitle": "",
		"Summary": "",
		"Description": "",
		"ChannelName": "ARD-alpha",
		"Start": "2018-09-13T07:00:00+02:00",
		"Stop": "2018-09-13T07:30:00+02:00",
		"Info": {}
	},
	{
		"Title": "Grundkurs Mathematik (5/15)",
		"Subtitle": "",
		"Summary": "",
		"Description": "",
		"ChannelName": "ARD-alpha",
		"Start": "2018-09-13T07:30:00+02:00",
		"Stop": "2018-09-13T08:00:00+02:00",
		"Info": {}
	},
	{
		"Title": "Tele-Gym",
		"Subtitle": "",
		"Summary": "",
		"Description": "",
		"ChannelName": "ARD-alpha",
		"Start": "2018-09-13T08:00:00+02:00",
		"Stop": "2018-09-13T08:15:00+02:00",
		"Info": {}
	},
	{
		"Title": "Panoramabilder",
		"Subtitle": "",
		"Summary": "",
		"Description": "",
		"ChannelName": "ARD-alpha",
		"Start": "2018-09-13T08:15:00+02:00",
		"Stop": "2018-09-13T09:30:00+02:00",
		"Info": {}
	},
	{
		"Title": "Schulfernsehen",
		"Subtitle": "",
		"Summary": "",
		"Description": "",
		"ChannelName": "ARD-alpha",
		"Start": "2018-09-13T09:30:00+02:00",
		"Stop": "2018-09-13T09:45:00+02:00",
		"Info": {}
	},
	{
		"Title": "Schulfernsehen",
		"Subtitle": "",
		"Summary": "",
		"Description": "",
		"ChannelName": "ARD-alpha",
		"Start": "2018-09-13T09:45:00+02:00",
		"Stop": "2018-09-13T10:00:00+02:00",
		"Info": {}
	},
	{
		"Title": "GRIPS Mathe",
		"Subtitle": "",
		"Summary": "",
		"Description": "",
		"ChannelName": "ARD-alpha",
		"Start": "2018-09-13T10:00:00+02:00",
		"Stop": "2018-09-13T10:15:00+02:00",
		"Info": {}
	},
	{
		"Title": "GRIPS Mathe",
		"Subtitle": "",
		"Summary": "",
		"Description": "",
		"ChannelName": "ARD-alpha",
		"Start": "2018-09-13T10:15:00+02:00",
		"Stop": "2018-09-13T10:30:00+02:00",
		"Info": {}
	},
	{
		"Title": "Campus",
		"Subtitle": "",
		"Summary": "",
		"Description": "",
		"ChannelName": "ARD-alpha",
		"Start": "2018-09-13T10:30:00+02:00",
		"Stop": "2018-09-13T11:00:00+02:00",
		"Info": {}
	},
	{
		"Title": "Planet Wissen: Welche Krankheiten kann die Genschere CRISPR heilen?",
		"Subtitle": "",
		"Summary": "",
		"Description": "",
		"ChannelName": "ARD-alpha",
		"Start": "2018-09-13T11:00:00+02:00",
		"Stop": "2018-09-13T12:05:00+02:00",
		"Info": {}
	},
	{
		"Title": "Tagesgespräch",
		"Subtitle": "",
		"Summary": "",
		"Description": "",
		"ChannelName": "ARD-alpha",
		"Start": "2018-09-13T12:05:00+02:00",
		"Stop": "2018-09-13T13:00:00+02:00",
		"Info": {}
	},
	{
		"Title": "Brandgefährlich (1/2)",
		"Subtitle": "",
		"Summary": "",
		"Description": "",
		"ChannelName": "ARD-alpha",
		"Start": "2018-09-13T13:00:00+02:00",
		"Stop": "2018-09-13T13:45:00+02:00",
		"Info": {}
	},
	{
		"Title": "Die Tierretter der Feuerwehr",
		"Subtitle": "",
		"Summary": "",
		"Description": "",
		"ChannelName": "ARD-alpha",
		"Start": "2018-09-13T13:45:00+02:00",
		"Stop": "2018-09-13T14:15:00+02:00",
		"Info": {}
	},
	{
		"Title": "Einfach clever: Wie Tiere denken (2/3)",
		"Subtitle": "",
		"Summary": "",
		"Description": "",
		"ChannelName": "ARD-alpha",
		"Start": "2018-09-13T14:15:00+02:00",
		"Stop": "2018-09-13T15:05:00+02:00",
		"Info": {}
	},
	{
		"Title": "Willi wills wissen",
		"Subtitle": "",
		"Summary": "",
		"Description": "",
		"ChannelName": "ARD-alpha",
		"Start": "2018-09-13T15:05:00+02:00",
		"Stop": "2018-09-13T15:30:00+02:00",
		"Info": {}
	},
	{
		"Title": "Paula und die wilden Tiere",
		"Subtitle": "",
		"Summary": "",
		"Description": "",
		"ChannelName": "ARD-alpha",
		"Start": "2018-09-13T15:30:00+02:00",
		"Stop": "2018-09-13T15:55:00+02:00",
		"Info": {}
	},
	{
		"Title": "Shaun das Schaf",
		"Subtitle": "",
		"Summary": "",
		"Description": "",
		"ChannelName": "ARD-alpha",
		"Start": "2018-09-13T15:55:00+02:00",
		"Stop": "2018-09-13T16:00:00+02:00",
		"Info": {}
	},
	{
		"Title": "alpha-retro: Auf der Autobahn",
		"Subtitle": "",
		"Summary": "",
		"Description": "",
		"ChannelName": "ARD-alpha",
		"Start": "2018-09-13T16:00:00+02:00",
		"Stop": "2018-09-13T16:30:00+02:00",
		"Info": {}
	},
	{
		"Title": "Einfach genial",
		"Subtitle": "",
		"Summary": "",
		"Description": "",
		"ChannelName": "ARD-alpha",
		"Start": "2018-09-13T16:30:00+02:00",
		"Stop": "2018-09-13T16:55:00+02:00",
		"Info": {}
	},
	{
		"Title": "Vom Ahorn bis zur Zwiebel",
		"Subtitle": "",
		"Summary": "",
		"Description": "",
		"ChannelName": "ARD-alpha",
		"Start": "2018-09-13T16:55:00+02:00",
		"Stop": "2018-09-13T17:00:00+02:00",
		"Info": {}
	},
	{
		"Title": "Quantensprung",
		"Subtitle": "",
		"Summary": "",
		"Description": "",
		"ChannelName": "ARD-alpha",
		"Start": "2018-09-13T17:00:00+02:00",
		"Stop": "2018-09-13T17:45:00+02:00",
		"Info": {}
	},
	{
		"Title": "nano",
		"Subtitle": "",
		"Summary": "",
		"Description": "",
		"ChannelName": "ARD-alpha",
		"Start": "2018-09-13T17:45:00+02:00",
		"Stop": "2018-09-13T18:15:00+02:00",
		"Info": {}
	},
	{
		"Title": "Planet Wissen: Alzheimer - Kampf gegen das große Vergessen",
		"Subtitle": "",
		"Summary": "",
		"Description": "",
		"ChannelName": "ARD-alpha",
		"Start": "2018-09-13T18:15:00+02:00",
		"Stop": "2018-09-13T19:15:00+02:00",
		"Info": {}
	},
	{
		"Title": "Verbrechen auf der Spur (4/5)",
		"Subtitle": "",
		"Summary": "",
		"Description": "",
		"ChannelName": "ARD-alpha",
		"Start": "2018-09-13T19:15:00+02:00",
		"Stop": "2018-09-13T19:30:00+02:00",
		"Info": {}
	},
	{
		"Title": "alpha-demokratie",
		"Subtitle": "",
		"Summary": "",
		"Description": "",
		"ChannelName": "ARD-alpha",
		"Start": "2018-09-13T19:30:00+02:00",
		"Stop": "2018-09-13T20:00:00+02:00",
		"Info": {}
	},
	{
		"Title": "Tagesschau",
		"Subtitle": "",
		"Summary": "",
		"Description": "",
		"ChannelName": "ARD-alpha",
		"Start": "2018-09-13T20:00:00+02:00",
		"Stop": "2018-09-13T20:15:00+02:00",
		"Info": {}
	},
	{
		"Title": "Einfach clever: Wie Tiere denken (3/3)",
		"Subtitle": "",
		"Summary": "",
		"Description": "",
		"ChannelName": "ARD-alpha",
		"Start": "2018-09-13T20:15:00+02:00",
		"Stop": "2018-09-13T21:05:00+02:00",
		"Info": {}
	},
	{
		"Title": "Brandgefährlich (2/2)",
		"Subtitle": "",
		"Summary": "",
		"Description": "",
		"ChannelName": "ARD-alpha",
		"Start": "2018-09-13T21:05:00+02:00",
		"Stop": "2018-09-13T21:50:00+02:00",
		"Info": {}
	},
	{
		"Title": "7 Tage bei der Feuerwehr",
		"Subtitle": "",
		"Summary": "",
		"Description": "",
		"ChannelName": "ARD-alpha",
		"Start": "2018-09-13T21:50:00+02:00",
		"Stop": "2018-09-13T22:20:00+02:00",
		"Info": {}
	},
	{
		"Title": "Campus Cinema",
		"Subtitle": "",
		"Summary": "",
		"Description": "",
		"ChannelName": "ARD-alpha",
		"Start": "2018-09-13T22:20:00+02:00",
		"Stop": "2018-09-13T22:50:00+02:00",
		"Info": {}
	},
	{
		"Title": "Gesundheit!",
		"Subtitle": "",
		"Summary": "",
		"Description": "",
		"ChannelName": "ARD-alpha",
		"Start": "2018-09-13T22:50:00+02:00",
		"Stop": "2018-09-13T23:20:00+02:00",
		"Info": {}
	},
	{
		"Title": "The Day - News in Review",
		"Subtitle": "",
		"Summary": "",
		"Description": "",
		"ChannelName": "ARD-alpha",
		"Start": "2018-09-13T23:20:00+02:00",
		"Stop": "2018-09-13T23:45:00+02:00",
		"Info": {}
	},
	{
		"Title": "Die Tagesschau vor 20 Jahren",
		"Subtitle": "",
		"Summary": "",
		"Description": "",
		"ChannelName": "ARD-alpha",
		"Start": "2018-09-13T23:45:00+02:00",
		"Stop": "2018-09-14T00:05:00+02:00",
		"Info": {}
	}
]