[
	{
		"Title": "Ray Donovan",
		"Subtitle": "",
		"Summary": "",
		"Description": "3. Staffel, Folge 12: Abby und Terry erz채hlen Ray von Bridgets Aff채re mit ihrem Mathelehrer. Sofort will Ray die Sache mit Gewalt beenden. Inzwischen formieren sich die Armenier zu einem Rachefeldzug gegen die Donovans. 57 Min.\nUSA 2015. Von David Hollander, mit Liev Schreiber, Paula Malcomson, Eddie Marsan.\nAb 18 Jahren",
		"ChannelName": "Sky Atlantic",
		"Start": "2018-09-13T00:35:00+02:00",
		"Stop": "2018-09-13T01:35:00+02:00",
		"Info": {}
	},
	{
		"Title": "Gigolos",
		"Subtitle": "",
		"Summary": "",
		"Description": "6. Staffel, Folge 6: Bradley hat ein Date mit einer Krankenschwester. Nick will sich als Country-Musiker versuchen. Vin trifft sich mit seinem Bruder. Brace muss f체r sein Date erstmal Hausarbeiten 체bernehmen. 26 Min.\nUSA 2015. Von John Downer, mit Vin Armani, Nick Hawk, Brace.\nAb 18 Jahren",
		"ChannelName": "Sky Atlantic",
		"Start": "2018-09-13T01:35:00+02:00",
		"Stop": "2018-09-13T02:05:00+02:00",
		"Info": {}
	}
]