[
	{
		"Title": "Schlimmer geht's immer mit Milo Murphy",
		"Subtitle": "",
		"Summary": "",
		"Description": "2. Staffel, Folge 1: Milo, Zack und Melissa müssen mit ihren neuen Nachbarn Phineas, Ferb, Buford und Baljeet zusammenarbeiten, um Murphys Gesetz zu überwinden und die Invasion der Pistazions zu stoppen.\nUSA 2017. 30 Min.",
		"ChannelName": "Disney XD",
		"Start": "2018-09-10T16:30:00+02:00",
		"Stop": "2018-09-10T17:00:00+02:00",
		"Info": {}
	},
	{
		"Title": "Big City Greens",
		"Subtitle": "",
		"Summary": "",
		"Description": "1. Staffel, Folge 11: Cricket macht einen Deal, um Bills Produkte an eine große Lebensmittelkette zu verkaufen.\nUSA 2017. 15 Min.",
		"ChannelName": "Disney XD",
		"Start": "2018-09-10T17:00:00+02:00",
		"Stop": "2018-09-10T17:15:00+02:00",
		"Info": {}
	},
	{
		"Title": "Big City Greens",
		"Subtitle": "",
		"Summary": "",
		"Description": "1. Staffel, Folge 10: Bill nutzt einen Ausflug zum Baumarkt, um Remy eine Lektion in Eigenständigkeit zu erteilen.\nUSA 2017. 15 Min.",
		"ChannelName": "Disney XD",
		"Start": "2018-09-10T17:15:00+02:00",
		"Stop": "2018-09-10T17:30:00+02:00",
		"Info": {}
	},
	{
		"Title": "Baymax: Robowabohu in Serie",
		"Subtitle": "",
		"Summary": "",
		"Description": "1. Staffel, Folge 13: Der verrückte Game-Show Moderator Mr. Sparkles droht Hiros Katze Mochi etwas anzutun, um Go Go dazu zu zwingen an einem Spiel teilzunehmen. Doch die hat eine riesen Angst vor öffentlichen Auftritten.\nUSA 2017. 30 Min.",
		"ChannelName": "Disney XD",
		"Start": "2018-09-10T17:30:00+02:00",
		"Stop": "2018-09-10T18:00:00+02:00",
		"Info": {}
	},
	{
		"Title": "S3 - Stärker, schneller, schlauer",
		"Subtitle": "",
		"Summary": "",
		"Description": "1. Staffel, Folge 86: Davenports Top-Wissenschaftler Dr. Ryan kommt auf die Akademie, um seine neueste Weltraumtechnologie zu testen. Es kommt zum Streit zwischen Chase und Dr. Ryan, was zu einem gravierenden Fehler in ihrer Arbeit führt und dafür sorgt, dass Davenport durch die Ozon-Schicht ins Weltall geschossen wird.\nUSA 2015. 30 Min. Von Hal Sparks, mit Maile Flanagan, Brandon Salgado-Telis, Mark Saul.",
		"ChannelName": "Disney XD",
		"Start": "2018-09-10T18:00:00+02:00",
		"Stop": "2018-09-10T18:30:00+02:00",
		"Info": {}
	},
	{
		"Title": "S3 - Stärker, schneller, schlauer",
		"Subtitle": "",
		"Summary": "",
		"Description": "1. Staffel, Folge 88: Chase und Douglas entdecken, dass Krane allen bionischen Schülern einen tödlichen Virus implantiert hat. Bald stellt sich heraus, dass dieser Virus auch in Adam, Chase und Bree schlummert.\nUSA 2015. 30 Min. Von Guy Distad, mit Jeremy Jackson, Ashley Argota.",
		"ChannelName": "Disney XD",
		"Start": "2018-09-10T18:30:00+02:00",
		"Stop": "2018-09-10T19:00:00+02:00",
		"Info": {}
	},
	{
		"Title": "Gamer's Guide für so ziemlich alles",
		"Subtitle": "",
		"Summary": "",
		"Description": "1. Staffel, Folge 11: Conor muss sich gemeinsam mit Ashley bei einem Tanzwettwettbewerb seiner größten Angst stellen.\nUSA 2015. 30 Min. Von Jason Earles, mit BooGie   , Laura Coover, Greg Perrow.",
		"ChannelName": "Disney XD",
		"Start": "2018-09-10T19:00:00+02:00",
		"Stop": "2018-09-10T19:30:00+02:00",
		"Info": {}
	},
	{
		"Title": "Karate-Chaoten",
		"Subtitle": "",
		"Summary": "",
		"Description": "1. Staffel, Folge 8: Kim gewinnt einen Wettbewerb und das Pop-Idol Ricky Weaver gibt ein Schulkonzert, bei dem sie mit ihm auf der Bühne tanzen soll. Jack möchte Kim vor Ricky warnen, der in ihr nur ein weiteres hübsches Mädchen sieht, das er erst küssen und dann abservieren will, doch Kim glaubt Jack kein Wort. In der Zwischenzeit gründen Rudy und die Jungs eine Boyband.\nUSA 2011. 30 Min.",
		"ChannelName": "Disney XD",
		"Start": "2018-09-10T19:30:00+02:00",
		"Stop": "2018-09-10T20:00:00+02:00",
		"Info": {}
	},
	{
		"Title": "Schlimmer geht's immer mit Milo Murphy",
		"Subtitle": "",
		"Summary": "",
		"Description": "2. Staffel, Folge 1: Milo, Zack und Melissa müssen mit ihren neuen Nachbarn Phineas, Ferb, Buford und Baljeet zusammenarbeiten, um Murphys Gesetz zu überwinden und die Invasion der Pistazions zu stoppen.\nUSA 2017. 30 Min.",
		"ChannelName": "Disney XD",
		"Start": "2018-09-10T20:00:00+02:00",
		"Stop": "2018-09-10T20:30:00+02:00",
		"Info": {}
	},
	{
		"Title": "Big City Greens",
		"Subtitle": "",
		"Summary": "",
		"Description": "1. Staffel, Folge 11: Cricket macht einen Deal, um Bills Produkte an eine große Lebensmittelkette zu verkaufen.\nUSA 2017. 15 Min.",
		"ChannelName": "Disney XD",
		"Start": "2018-09-10T20:30:00+02:00",
		"Stop": "2018-09-10T20:45:00+02:00",
		"Info": {}
	},
	{
		"Title": "Big City Greens",
		"Subtitle": "",
		"Summary": "",
		"Description": "1. Staffel, Folge 10: Bill nutzt einen Ausflug zum Baumarkt, um Remy eine Lektion in Eigenständigkeit zu erteilen.\nUSA 2017. 15 Min.",
		"ChannelName": "Disney XD",
		"Start": "2018-09-10T20:45:00+02:00",
		"Stop": "2018-09-10T21:00:00+02:00",
		"Info": {}
	},
	{
		"Title": "Spider-Man",
		"Subtitle": "",
		"Summary": "",
		"Description": "1. Staffel, Folge 4: Norman Osborn gründet die Osborn Academy für Genies, um seinen Sohn Harry von der Schande zu befreien, von der Horizon High suspendiert worden zu sein.\nUSA 2017. 30 Min.",
		"ChannelName": "Disney XD",
		"Start": "2018-09-10T21:00:00+02:00",
		"Stop": "2018-09-10T21:30:00+02:00",
		"Info": {}
	},
	{
		"Title": "Star Wars Rebels",
		"Subtitle": "",
		"Summary": "",
		"Description": "3. Staffel, Folge 2: Angeführt von einem mächtigeren Ezra befreien die Rebellen einen alten Freund aus dem Gefängnis, um ihnen zu helfen, an Schiffe für ihre Flotte zu gelangen. Allerdings bemerkt Kanan, dass Ezras neue Fähigkeiten einer dunklen Quelle entspringen.\nUSA 2016. 30 Min.",
		"ChannelName": "Disney XD",
		"Start": "2018-09-10T21:30:00+02:00",
		"Stop": "2018-09-10T22:00:00+02:00",
		"Info": {}
	},
	{
		"Title": "Phil aus der Zukunft",
		"Subtitle": "",
		"Summary": "",
		"Description": "1. Staffel, Folge 4: Pam und Debbie glauben, dass sich ihr Lehrer Mr. Hackett einer schlimmen Operation unterziehen muss und sammeln für ihn Geld. Als sie aber entdecken, dass er sich nur eine Haartransplantation machen lassen will, nehmen sie es ihm wieder weg. Phil kann an einem Ausflug zu einer Tomatenranch nicht teilnehmen, als Keely im sagt, dass zum Schluss alle barfuss die Tomaten stampfen müssen. Er hat nämlich, wie alle Leute aus der Zukunft, nur 4 Zehen und befürchtet, dass das Familiengeheimnis gelüftet wird.\nUSA 2003. 25 Min. Von Tim O'Donnell.",
		"ChannelName": "Disney XD",
		"Start": "2018-09-10T22:00:00+02:00",
		"Stop": "2018-09-10T22:25:00+02:00",
		"Info": {}
	},
	{
		"Title": "Future-Worm!",
		"Subtitle": "",
		"Summary": "",
		"Description": "1. Staffel, Folge 19: (a) Future Worms Techtelmechtel mit seiner neuen Flamme Uga, der Höhlenfrau, droht, den Zeitreisenausflug, den Danny mit ihm vorhatte, empfindlich zu stören. (b) Future-Worm verliert seinen Körper - und Zarlid bekommt ihn! (c) Steak Starbolt agiert als intergalaktischer Präsident, um einen Krieg zu beenden.\nUSA 2015. 25 Min.",
		"ChannelName": "Disney XD",
		"Start": "2018-09-10T22:25:00+02:00",
		"Stop": "2018-09-10T22:50:00+02:00",
		"Info": {}
	},
	{
		"Title": "Mein Geist rockt!",
		"Subtitle": "",
		"Summary": "",
		"Description": "1. Staffel, Folge 10: (a) Spencer überredet seine Eltern, dass er ohne Babysitter allein zu Hause bleiben darf, als sie für ein paar Tage verreisen. (b) Spencer will den Aerobikkurs von Rektor Ponzi verlassen, aber das ist nur möglich, wenn er einen Platz im Wrestling Team der Schule ergattert.   \nF 2012. 25 Min. Von Frédéric Martin.",
		"ChannelName": "Disney XD",
		"Start": "2018-09-10T22:50:00+02:00",
		"Stop": "2018-09-10T23:15:00+02:00",
		"Info": {}
	},
	{
		"Title": "Mein Geist rockt!",
		"Subtitle": "",
		"Summary": "",
		"Description": "1. Staffel, Folge 11: (a) Als Hugh Spencers Wettbewerbsbeitrag zum Wettbewerb für junge Filmemacher ruiniert, ist Spencer gezwungen, einen neuen Film zu drehen - aber er hat nicht mal einen Tag Zeit dafür. (b) Billys Pelzmantel verwandelt Spencer in einen Werwolf. Leider wird am selben Tag auch das Klassenfoto gemacht.      \nF 2012. 25 Min. Von Frédéric Martin.",
		"ChannelName": "Disney XD",
		"Start": "2018-09-10T23:15:00+02:00",
		"Stop": "2018-09-10T23:40:00+02:00",
		"Info": {}
	},
	{
		"Title": "Randy Cunningham: Der Ninja aus der 9. Klasse",
		"Subtitle": "",
		"Summary": "",
		"Description": "1. Staffel, Folge 23: (a) Während des 'Ninja-Tages' in Norrisville, versucht sich McFist ins Rampenlicht zu drängen, indem er sich selbst als den neuen Superhelden 'Lucius Donnerfaust' vorstellt (b) Kürzlich sagte Randy dem Sumpf-Hexer Catfish Booray, dass sein wahrer Name Rainald Bangel ist. Was Randy jedoch nicht wusste: Es gibt wirklich einen Jungen auf seiner Schule der so heißt! McFist hat deshalb seinen Vollstrecker-Roboter ausgesendet, der Rainald suchen und zerstören soll. Wird Randy Rainald retten können?\nGB 2013. 25 Min. Von Joshua Taback.",
		"ChannelName": "Disney XD",
		"Start": "2018-09-10T23:40:00+02:00",
		"Stop": "2018-09-11T00:05:00+02:00",
		"Info": {}
	}
]