[
	{
		"Title": "RuhePULS",
		"Subtitle": "",
		"Summary": "",
		"Description": "",
		"ChannelName": "PULS",
		"Start": "2018-09-15T00:00:00+02:00",
		"Stop": "2018-09-15T08:00:00+02:00",
		"Info": {}
	},
	{
		"Title": "Diese neue Musik",
		"Subtitle": "",
		"Summary": "",
		"Description": "",
		"ChannelName": "PULS",
		"Start": "2018-09-15T08:00:00+02:00",
		"Stop": "2018-09-15T12:00:00+02:00",
		"Info": {}
	},
	{
		"Title": "Netzfilter",
		"Subtitle": "",
		"Summary": "",
		"Description": "",
		"ChannelName": "PULS",
		"Start": "2018-09-15T12:00:00+02:00",
		"Stop": "2018-09-15T14:00:00+02:00",
		"Info": {}
	},
	{
		"Title": "Plus1",
		"Subtitle": "",
		"Summary": "",
		"Description": "",
		"ChannelName": "PULS",
		"Start": "2018-09-15T14:00:00+02:00",
		"Stop": "2018-09-15T18:00:00+02:00",
		"Info": {}
	},
	{
		"Title": "Die Schacht \u0026 Wasabi Show",
		"Subtitle": "",
		"Summary": "",
		"Description": "",
		"ChannelName": "PULS",
		"Start": "2018-09-15T18:00:00+02:00",
		"Stop": "2018-09-15T20:00:00+02:00",
		"Info": {}
	},
	{
		"Title": "Die Falk Schacht Show",
		"Subtitle": "",
		"Summary": "",
		"Description": "",
		"ChannelName": "PULS",
		"Start": "2018-09-15T20:00:00+02:00",
		"Stop": "2018-09-15T22:00:00+02:00",
		"Info": {}
	},
	{
		"Title": "Kammerflimmern mit Wildstyle",
		"Subtitle": "",
		"Summary": "",
		"Description": "",
		"ChannelName": "PULS",
		"Start": "2018-09-15T22:00:00+02:00",
		"Stop": "2018-09-16T00:00:00+02:00",
		"Info": {}
	}
]