[
	{
		"Title": "WDR aktuell",
		"Subtitle": "",
		"Summary": "",
		"Description": "",
		"ChannelName": "WDR 3",
		"Start": "2018-09-15T00:00:00+02:00",
		"Stop": "2018-09-15T00:05:00+02:00",
		"Info": {}
	},
	{
		"Title": "Das ARD Nachtkonzert",
		"Subtitle": "",
		"Summary": "",
		"Description": "",
		"ChannelName": "WDR 3",
		"Start": "2018-09-15T00:05:00+02:00",
		"Stop": "2018-09-15T06:00:00+02:00",
		"Info": {}
	},
	{
		"Title": "WDR aktuell",
		"Subtitle": "",
		"Summary": "",
		"Description": "",
		"ChannelName": "WDR 3",
		"Start": "2018-09-15T06:00:00+02:00",
		"Stop": "2018-09-15T06:04:00+02:00",
		"Info": {}
	},
	{
		"Title": "WDR 3 Mosaik",
		"Subtitle": "",
		"Summary": "",
		"Description": "",
		"ChannelName": "WDR 3",
		"Start": "2018-09-15T06:04:00+02:00",
		"Stop": "2018-09-15T09:00:00+02:00",
		"Info": {}
	},
	{
		"Title": "WDR aktuell",
		"Subtitle": "",
		"Summary": "",
		"Description": "",
		"ChannelName": "WDR 3",
		"Start": "2018-09-15T09:00:00+02:00",
		"Stop": "2018-09-15T09:04:00+02:00",
		"Info": {}
	},
	{
		"Title": "WDR 3 Klassik Forum",
		"Subtitle": "",
		"Summary": "",
		"Description": "",
		"ChannelName": "WDR 3",
		"Start": "2018-09-15T09:04:00+02:00",
		"Stop": "2018-09-15T12:00:00+02:00",
		"Info": {}
	},
	{
		"Title": "WDR aktuell",
		"Subtitle": "",
		"Summary": "",
		"Description": "",
		"ChannelName": "WDR 3",
		"Start": "2018-09-15T12:00:00+02:00",
		"Stop": "2018-09-15T12:04:00+02:00",
		"Info": {}
	},
	{
		"Title": "WDR 3 Kulturfeature",
		"Subtitle": "",
		"Summary": "",
		"Description": "",
		"ChannelName": "WDR 3",
		"Start": "2018-09-15T12:04:00+02:00",
		"Stop": "2018-09-15T13:00:00+02:00",
		"Info": {}
	},
	{
		"Title": "WDR aktuell",
		"Subtitle": "",
		"Summary": "",
		"Description": "",
		"ChannelName": "WDR 3",
		"Start": "2018-09-15T13:00:00+02:00",
		"Stop": "2018-09-15T13:04:00+02:00",
		"Info": {}
	},
	{
		"Title": "WDR 3 Persönlich mit Götz Alsmann",
		"Subtitle": "",
		"Summary": "",
		"Description": "",
		"ChannelName": "WDR 3",
		"Start": "2018-09-15T13:04:00+02:00",
		"Stop": "2018-09-15T15:00:00+02:00",
		"Info": {}
	},
	{
		"Title": "WDR aktuell",
		"Subtitle": "",
		"Summary": "",
		"Description": "",
		"ChannelName": "WDR 3",
		"Start": "2018-09-15T15:00:00+02:00",
		"Stop": "2018-09-15T15:04:00+02:00",
		"Info": {}
	},
	{
		"Title": "WDR 3 Gutenbergs Welt",
		"Subtitle": "",
		"Summary": "",
		"Description": "",
		"ChannelName": "WDR 3",
		"Start": "2018-09-15T15:04:00+02:00",
		"Stop": "2018-09-15T16:00:00+02:00",
		"Info": {}
	},
	{
		"Title": "WDR aktuell",
		"Subtitle": "",
		"Summary": "",
		"Description": "",
		"ChannelName": "WDR 3",
		"Start": "2018-09-15T16:00:00+02:00",
		"Stop": "2018-09-15T16:04:00+02:00",
		"Info": {}
	},
	{
		"Title": "WDR 3 Lesung",
		"Subtitle": "",
		"Summary": "",
		"Description": "",
		"ChannelName": "WDR 3",
		"Start": "2018-09-15T16:04:00+02:00",
		"Stop": "2018-09-15T17:00:00+02:00",
		"Info": {}
	},
	{
		"Title": "WDR aktuell",
		"Subtitle": "",
		"Summary": "",
		"Description": "",
		"ChannelName": "WDR 3",
		"Start": "2018-09-15T17:00:00+02:00",
		"Stop": "2018-09-15T17:04:00+02:00",
		"Info": {}
	},
	{
		"Title": "WDR 3 Vesper I",
		"Subtitle": "",
		"Summary": "",
		"Description": "",
		"ChannelName": "WDR 3",
		"Start": "2018-09-15T17:04:00+02:00",
		"Stop": "2018-09-15T17:45:00+02:00",
		"Info": {}
	},
	{
		"Title": "WDR 3 ZeitZeichen",
		"Subtitle": "",
		"Summary": "",
		"Description": "",
		"ChannelName": "WDR 3",
		"Start": "2018-09-15T17:45:00+02:00",
		"Stop": "2018-09-15T18:00:00+02:00",
		"Info": {}
	},
	{
		"Title": "WDR aktuell",
		"Subtitle": "",
		"Summary": "",
		"Description": "",
		"ChannelName": "WDR 3",
		"Start": "2018-09-15T18:00:00+02:00",
		"Stop": "2018-09-15T18:04:00+02:00",
		"Info": {}
	},
	{
		"Title": "WDR 3 Vesper II",
		"Subtitle": "",
		"Summary": "",
		"Description": "",
		"ChannelName": "WDR 3",
		"Start": "2018-09-15T18:04:00+02:00",
		"Stop": "2018-09-15T19:00:00+02:00",
		"Info": {}
	},
	{
		"Title": "WDR aktuell",
		"Subtitle": "",
		"Summary": "",
		"Description": "",
		"ChannelName": "WDR 3",
		"Start": "2018-09-15T19:00:00+02:00",
		"Stop": "2018-09-15T19:04:00+02:00",
		"Info": {}
	},
	{
		"Title": "WDR 3 Hörspiel",
		"Subtitle": "",
		"Summary": "",
		"Description": "",
		"ChannelName": "WDR 3",
		"Start": "2018-09-15T19:04:00+02:00",
		"Stop": "2018-09-15T20:00:00+02:00",
		"Info": {}
	},
	{
		"Title": "WDR aktuell",
		"Subtitle": "",
		"Summary": "",
		"Description": "",
		"ChannelName": "WDR 3",
		"Start": "2018-09-15T20:00:00+02:00",
		"Stop": "2018-09-15T20:04:00+02:00",
		"Info": {}
	},
	{
		"Title": "WDR 3 Konzert",
		"Subtitle": "",
		"Summary": "",
		"Description": "",
		"ChannelName": "WDR 3",
		"Start": "2018-09-15T20:04:00+02:00",
		"Stop": "2018-09-15T22:00:00+02:00",
		"Info": {}
	},
	{
		"Title": "WDR aktuell",
		"Subtitle": "",
		"Summary": "",
		"Description": "",
		"ChannelName": "WDR 3",
		"Start": "2018-09-15T22:00:00+02:00",
		"Stop": "2018-09-15T22:04:00+02:00",
		"Info": {}
	},
	{
		"Title": "WDR 3 Open Sounds: Studio Elektronische Musik",
		"Subtitle": "",
		"Summary": "",
		"Description": "",
		"ChannelName": "WDR 3",
		"Start": "2018-09-15T22:04:00+02:00",
		"Stop": "2018-09-16T00:00:00+02:00",
		"Info": {}
	}
]